{
  "s_type": "game",
  "i_nid": 97802,
  "s_title": "Cyber Knight",
  "s_synopsis": "In the 24th century, mankind has gone into space. The crew of the starship Swordfish are in an engagement with space pirates when the battle takes a turn for the worse. In desperation, the crew activate their jump drive without a destination... and end up flung across the galaxy to the galactic core. The Swordfish however is badly damaged with many casualties including the captain. Only 26 of the crew survive, and of them only six are qualified for combat: The commander, two soldiers, a mechanic and a doctor and six giant &quot;Module&quot; mechanized suits available for them. These survivors locate planet Farworld, apparently colonized by humans. There they discover the colony is under attack by a relentless mechanical aliens dubbed &quot;Berserkers&quot;. The crew of the Swordfish must fight back against the Berserkers and explore the galaxy for some means to return home.",
  "as_genres": [
    "role play"
  ],
  "ai_sagas": [
    97803
  ]
}