{
  "s_type": "game",
  "i_nid": 71368,
  "s_title": "Inferno",
  "s_synopsis": "&quot;Inferno&quot; continues the story-line of the Raxxon - Terran conflict that began at the time of &quot;Epic&quot;. The premise offers more plot developments than the original game: you are a Terran pilot who was ambushed by the Raxxons, who transformed you surgically into one of their own. Enraged, you killed all the Raxxons on board the station to regain your human form. With renewed vigor and thirst for revenge, you vow to eliminate their race once and for all...\r\n",
  "as_genres": [
    "simulation"
  ],
  "ai_sagas": [
    71369
  ]
}