{
  "s_type": "game",
  "s_status": "open",
  "i_nid": 80823,
  "s_title": "Mystery Dungeon - Shiren the Wanderer",
  "s_synopsis": "The legend of the Golden Condor... from village to village and from town to town, everybody speak of it - somewhere, beyond forests and mountains, there lies an idyllic Golden Land, the land of eternal happiness. Many adventurers have tried to find their way to the mysterious land of the Golden Condor, but how many of them have survived the impassable mountain paths, the dark forests and caves, and the vicious monsters? You are the wanderer Shiren, and the goal of your life is to find the Golden Land. Together with your best buddy Koppa, a talking weasel, you decide to venture deep into the dungeons that lead to the land, and to try your luck there.",
  "as_genres": [
    "action",
    "role play"
  ],
  "ai_sagas": []
}