{
  "s_type": "game",
  "i_nid": 47943,
  "s_title": "Rally de Africa",
  "s_synopsis": "&quot;Rally de Africa&quot; is an arcade rally racing game that features four modes: Championship, where the player plays through a series of races; Spot Entry, where the player can play a singe race; 2 Player Battle, where two players can race against each other; and Memory Battle, where the player can race against the replay of another player which is stored on the memory card. In each race you begin in the twelfth position behind eleven computer opponents, the goal is to pass all the opponents to get into the first place position before you reach the end of the stage. The game features a total of five different stages set across the continent of Africa and a selection of unlicensed vehicles to race with.\r\n",
  "as_genres": [
    "racing"
  ],
  "ai_sagas": [
    47942
  ]
}