{
  "s_type": "game",
  "i_nid": 48958,
  "s_title": "Runabout 2",
  "s_synopsis": "In the sequel to Felony 11-79, you are hired by a secret organization which asks you to do certain tasks in a variety of environments, ranging from a downtown city to a desert. Like the original, you can drive around like a maniac and smash into everything you see. You receive e-mail from various contacts, who give out advice on how to do the mission.",
  "s_years": "2000",
  "as_genres": [
    "racing"
  ],
  "ao_sagas": [
    {
      "s_type": "saga",
      "i_nid": 48958,
      "s_title": "Runabout",
      "s_synopsis": null,
      "s_years": null,
      "ao_games": null
    }
  ],
  "ai_versions": [
    18769,
    85319,
    18770,
    18950,
    21909
  ]
}