{
  "s_type": "game",
  "i_nid": 74344,
  "s_title": "Future Wars",
  "s_synopsis": "In the 43rd century Earth is under attack from an alien race. The planet is well protected by a formidable SDI defence which the aliens cannot penetrate... until they hit on a plan... sabotage the defences BEFORE they are built by travelling back in time to plant delayed-action bombs at strategic places! Your adventure starts in the present day when, innocently attempting to avoid your boss at work you stumble across a secret passage that transports you back in time to the start of a quest that takes you into the Middle Ages, Prehistoric Times, and the distant future. ",
  "s_years": "????",
  "as_genres": [
    "graphic adventure"
  ],
  "ao_sagas": [],
  "ai_versions": [
    36863,
    36864,
    51066,
    36861,
    39017,
    52248,
    36862,
    49252,
    36860,
    50382
  ]
}