{
  "s_type": "game",
  "i_nid": 41238,
  "s_title": "Cybernoid II - The Revenge",
  "s_synopsis": "The follow-up to &quot;Cybernoid: The Fighting Machine&quot; is again a flip-screen shoot &#039;em up. In control of the deadly Cybernoid craft, your job is to rescue the cargo which has been stolen by a wave of pirate ships.",
  "s_years": "1989",
  "as_genres": [
    "shooter"
  ],
  "ao_sagas": [
    {
      "s_type": "saga",
      "i_nid": 41238,
      "s_title": "Cybernoid",
      "s_synopsis": null,
      "s_years": null,
      "ao_games": null
    }
  ],
  "ai_versions": [
    25921,
    36449
  ]
}