{
  "s_type": "game",
  "i_nid": 40114,
  "s_title": "U.N. Squadron",
  "s_synopsis": "Side-scrolling shoot-em-up, in a similar style to such games as Gradius, R-Type and Scramble. The aim is to wipe out the enemy, which has gathered around the allied airspace of &quot;Area 88&quot;, in a series of military aircraft-based scenarios. You choose one of three unique pilots; Shin Kazama, Micky Schymon or Greg Gates, each with varying abilities at damage repair, weapon handling and flying skill, and engage the enemy over a series of challenging missions. ",
  "as_genres": [
    "shooter"
  ],
  "ai_sagas": []
}