{
  "s_type": "game",
  "i_nid": 47684,
  "s_title": "Spyro - Year of the Dragon",
  "s_synopsis": "The third entry into the Dragon series sees Spyro having to recover a clutch of Dragon eggs from the evil Sorceress. The player can now play as not only Spyro, but Agent 9 the Space Monkey, Sheila the Kangaroo, Bentley the Yeti, Sgt. Byrd the Penguin and his two best friends Sparx and Hunter. Sparx has his own levels for the very first time. Also, Spyro has learned a few new abilities, including skateboarding!",
  "as_genres": [
    "platforms"
  ],
  "ai_sagas": []
}