{
  "s_type": "game",
  "s_status": "open",
  "i_nid": 85530,
  "s_title": "Eternal Champions - Challenge from the Dark Side",
  "s_synopsis": "The Dark Champion knows your greatest fear! As one of the greatest fighters in history, you have been brought back to life to do battle with the Dark Champion. Resist his evil power or he will use your own greatest fear against you. Four ways to finish your opponent: vicious Overkills, shocking Sudden Deaths, ultra-personal Vendettas, and brutally graphic Cinekills! Includes all nine original characters, plus four new fighters and 11 hidden characters! Every champion has his or her own real martial arts style like Kenpo Karate, Tae Kwon Do, Thai Kickboxing and more!",
  "as_genres": [
    "vs. fighting"
  ],
  "ai_sagas": [
    85529
  ]
}