{
  "s_type": "game",
  "s_status": "open",
  "i_nid": 46621,
  "s_title": "Battle Mania Daiginjo",
  "s_synopsis": "The Trouble Shooters, Mania Otori and Maria Haneda, are a pair of bounty hunters who will take any job that involves lots of trouble and plenty of shooting. Their last job saw them saving the Crown Prince Denka from the evil military mastermind Don Morguestein, presumably ending his evil plans. However, three days later, Morguestein has returned once more to take revenge upon the Trouble Shooters. Mania and Maria, never wanting to miss out on the action, head off to take care of him once and for all.",
  "as_genres": [
    "shooter"
  ],
  "ai_sagas": [
    46622
  ]
}