{
  "s_type": "game",
  "s_status": "open",
  "i_nid": 101130,
  "s_title": "Foreman For Real",
  "s_synopsis": "Pay attention, pug: this is the biggest fight of your life! Your facing 20 of the toughest boxers in the world, and each packs a powerful punch! If you get past them, you got &quot;Big&quot; George Foreman and the title waiting! This ain&#039;t no club fight: Acclaim&#039;s motion capture technology makes this the most authentic action you&#039;ve ever experienced! So get in there, get tough, and get real: Foreman For Real!",
  "as_genres": [
    "vs. fighting"
  ],
  "ai_sagas": []
}