{
  "s_type": "game",
  "s_status": "open",
  "i_nid": 85843,
  "s_title": "Jurassic Park Part 2 - The Chaos Continues",
  "s_synopsis": "One year after the events of the Jurassic Park, John Hammond wants to bring Jurassic Park back and he sends Dr. Alan Grant to aid a team of heavy armed men down to the former park to restore order. Meanwhile, Biosyn Corp has sent men down the former park so the company can gain control of the park for themselves.",
  "as_genres": [
    "action",
    "shooter"
  ],
  "ai_sagas": [
    85467
  ]
}