{
  "s_type": "game",
  "s_status": "open",
  "i_nid": 45080,
  "s_title": "Langrisser II",
  "s_synopsis": "The events of the game take place several years after those described in Langrisser. Gone is the benevolent kingdom of Baltia, and a new power has risen - the Rayguard Empire, which has made a pact with the malevolent Lord B\u00f6ser, whose intention is to find the most powerful evil sword in the land, the Alhazard. The main hero of the game, the knight Elwin, must help the Descendants of Light to retrieve the legendary holy sword Langrisser, the only artifact that is more powerful than Alhazard. ",
  "as_genres": [
    "role play"
  ],
  "ai_sagas": [
    45081
  ]
}